alu.v
// 4 -bit ALU - 8 OPERATIONS
module alu(input [3:0] a,b, output reg [3:0]out, 
input [2:0] sel);   //sel[2:0] = Operation select

always@(*)begin

    case(sel) 
        3'b000: out=a&b;       //and operation
        3'b001: out=a|b;       //or operation
        3'b010: out=a^b;       //xor operation
        3'b011: out=~(a&b);    //nand operation
        3'b100: out=~(a|b);    //nor operation
        3'b101: out=a-b;       //subtraction operation(difference not captured)
        3'b110: out=~a;        //not a operation
        3'b111: out=a+b;       //addition operation(carry not captured)
        default: out = 4'b0000;
    endcase


end

endmodule

alu_tb.v
module test;
reg[3:0] a,b;
reg [2:0]sel;
wire [3:0]out;

alu uut(.a(a),.b(b),.sel(sel),.out(out));
    
    
    initial begin
        a=0 ; b=0 ; sel=0;

        sel = 3'b000;
        #10 a=4'b0001 ; b=4'b1001 ;
        #10 a=4'b1001 ; b=4'b1101 ;

        sel = 3'b001;
        #10 a=4'b0001 ; b=4'b1001 ;
        #10 a=4'b1001 ; b=4'b1101 ;

        sel = 3'b010;
        #10 a=4'b0001 ; b=4'b1001 ;
        #10 a=4'b1001 ; b=4'b1101 ;

        sel =3'b011;
        #10 a=4'b0001 ; b=4'b1001 ;
        #10 a=4'b1001 ; b=4'b1101 ;

        sel = 3'b100;
       #10 a=4'b0001 ; b=4'b1001 ;
        #10 a=4'b1001 ; b=4'b1101 ;

        sel = 3'b101;
        #10 a=4'b0001 ; b=4'b1001 ;
        #10 a=4'b1001 ; b=4'b1101 ;

        sel = 3'b110;
        #10 a=4'b0001 ; b=4'b1001 ;
        #10 a=4'b1001 ; b=4'b1101 ;

        sel = 3'b111;
        #10 a=4'b0001 ; b=4'b1001 ;
        #10 a=4'b1001 ; b=4'b1101 ;

        #10 $finish ;
    end

    initial begin
        $dumpfile("aluwave.vcd");
        $dumpvars(0, test);
        $monitor("t=%0t sel=%b a=%0d b=%0d out=%0d", $time ,sel ,a,b,out);
    end

endmodule

aluwave.vcd
$date
	Sat May 02 19:35:52 2026
$end
$version
	Icarus Verilog
$end
$timescale
	1s
$end
$scope module test $end
$var wire 4 ! out [3:0] $end
$var reg 4 " a [3:0] $end
$var reg 4 # b [3:0] $end
$var reg 3 $ sel [2:0] $end
$scope module uut $end
$var wire 4 % a [3:0] $end
$var wire 4 & b [3:0] $end
$var wire 3 ' sel [2:0] $end
$var reg 4 ( out [3:0] $end
$upscope $end
$upscope $end
$enddefinitions $end
#0
$dumpvars
b0 (
b0 '
b0 &
b0 %
b0 $
b0 #
b0 "
b0 !
$end
#10
b1 !
b1 (
b1001 #
b1001 &
b1 "
b1 %
#20
b1101 !
b1101 (
b1 $
b1 '
b1101 #
b1101 &
b1001 "
b1001 %
#30
b1001 !
b1001 (
b1001 #
b1001 &
b1 "
b1 %
#40
b100 !
b100 (
b10 $
b10 '
b1101 #
b1101 &
b1001 "
b1001 %
#50
b1000 !
b1000 (
b1001 #
b1001 &
b1 "
b1 %
#60
b110 !
b110 (
b11 $
b11 '
b1101 #
b1101 &
b1001 "
b1001 %
#70
b1110 !
b1110 (
b1001 #
b1001 &
b1 "
b1 %
#80
b10 !
b10 (
b100 $
b100 '
b1101 #
b1101 &
b1001 "
b1001 %
#90
b110 !
b110 (
b1001 #
b1001 &
b1 "
b1 %
#100
b1100 !
b1100 (
b101 $
b101 '
b1101 #
b1101 &
b1001 "
b1001 %
#110
b1000 !
b1000 (
b1001 #
b1001 &
b1 "
b1 %
#120
b110 !
b110 (
b110 $
b110 '
b1101 #
b1101 &
b1001 "
b1001 %
#130
b1110 !
b1110 (
b1001 #
b1001 &
b1 "
b1 %
#140
b110 !
b110 (
b111 $
b111 '
b1101 #
b1101 &
b1001 "
b1001 %
#150
b1010 !
b1010 (
b1001 #
b1001 &
b1 "
b1 %
#160
b110 !
b110 (
b1101 #
b1101 &
b1001 "
b1001 %
